pyheic_struct/__init__.py
pyheic_struct/__main__.py
pyheic_struct/base.py
pyheic_struct/builder.py
pyheic_struct/cli.py
pyheic_struct/converter.py
pyheic_struct/heic_file.py
pyheic_struct/heic_types.py
pyheic_struct/parser.py
pyheic_struct/handlers/__init__.py
pyheic_struct/handlers/apple_handler.py
pyheic_struct/handlers/base_handler.py
pyheic_struct/handlers/samsung_handler.py
pyheic_struct/targets/__init__.py
pyheic_struct/targets/apple.py
pyheic_struct/targets/base.py
pyheic_struct-0.1.0.dist-info/METADATA
pyheic_struct-0.1.0.dist-info/WHEEL
pyheic_struct-0.1.0.dist-info/entry_points.txt
pyheic_struct-0.1.0.dist-info/top_level.txt
pyheic_struct-0.1.0.dist-info/RECORD
